txrm2tiff/__init__.py
txrm2tiff/__main__.py
txrm2tiff/info.py
txrm2tiff/inspector.py
txrm2tiff/main.py
txrm2tiff/font/CallingCode-Regular.otf
txrm2tiff/txrm/__init__.py
txrm2tiff/txrm/abstract.py
txrm2tiff/txrm/annot_mixin.py
txrm2tiff/txrm/main.py
txrm2tiff/txrm/ref_mixin.py
txrm2tiff/txrm/save_mixin.py
txrm2tiff/txrm/shifts_mixin.py
txrm2tiff/txrm/txrm_property.py
txrm2tiff/txrm/v3.py
txrm2tiff/txrm/v5.py
txrm2tiff/txrm_functions/__init__.py
txrm2tiff/txrm_functions/general.py
txrm2tiff/txrm_functions/images.py
txrm2tiff/utils/__init__.py
txrm2tiff/utils/file_handler.py
txrm2tiff/utils/functions.py
txrm2tiff/utils/image_processing.py
txrm2tiff/utils/logging.py
txrm2tiff/utils/metadata.py
txrm2tiff/utils/shortcut_creation.py
txrm2tiff/xradia_properties/__init__.py
txrm2tiff/xradia_properties/enums.py
txrm2tiff/xradia_properties/stream_dtypes.py
txrm2tiff-2.2.0.dist-info/LICENSE
txrm2tiff-2.2.0.dist-info/METADATA
txrm2tiff-2.2.0.dist-info/WHEEL
txrm2tiff-2.2.0.dist-info/entry_points.txt
txrm2tiff-2.2.0.dist-info/top_level.txt
txrm2tiff-2.2.0.dist-info/RECORD
