Metadata-Version: 2.1
Name: txrm2tiff
Version: 2.2.0
Summary: A converter for Zeiss txrm and xrm files, created by & for B24 of Diamond Light Source
Author-email: Thomas Fish <thomas.fish@diamond.ac.uk>
License: BSD-3-Clause
Classifier: Programming Language :: Python :: 3
Classifier: License :: OSI Approved :: BSD License
Classifier: Operating System :: OS Independent
Requires-Python: >=3.10
License-File: LICENSE
Requires-Dist: tifffile>=2022.7.28
Requires-Dist: numpy>=1.24.4
Requires-Dist: omexml-dls>=1.1.0
Requires-Dist: olefile>=0.46
Requires-Dist: scipy>=1.3.3
Requires-Dist: pillow>=11
Requires-Dist: pywin32; platform_system == "Windows"
